cloudops/__init__.py
cloudops/toolkit.py
cloudops101-0.1.1.dist-info/METADATA
cloudops101-0.1.1.dist-info/WHEEL
cloudops101-0.1.1.dist-info/top_level.txt
cloudops101-0.1.1.dist-info/RECORD
