Metadata-Version: 2.1
Name: cloudops101
Version: 0.1.1
Summary: CloudOps Automation for DevOps and SRE teams.
Author-email: cloudops101 maintainers <nnthanh101@gmail.com>
Classifier: Development Status :: 4 - Beta
Classifier: Environment :: Console
Classifier: License :: OSI Approved :: Apache Software License
Classifier: Operating System :: OS Independent
Classifier: Programming Language :: Python :: 3
Classifier: Programming Language :: Python :: 3.11
Classifier: Programming Language :: Python :: 3.12
Classifier: Topic :: Documentation
Classifier: Topic :: Software Development :: Libraries :: Python Modules
Classifier: Topic :: Utilities
Requires-Python: >=3.12
Requires-Dist: requests>=2.32.3
Requires-Dist: loguru>=0.7.3
Requires-Dist: typer>=0.15.1
Requires-Dist: tqdm>=4.67.1
Requires-Dist: boto3>=1.35.90
Requires-Dist: moto>=5.0.25
